django_enterprise_maintenance_suite/__init__.py
django_enterprise_maintenance_suite/admin.py
django_enterprise_maintenance_suite/apps.py
django_enterprise_maintenance_suite/backends.py
django_enterprise_maintenance_suite/manager.py
django_enterprise_maintenance_suite/middleware.py
django_enterprise_maintenance_suite/models.py
django_enterprise_maintenance_suite/signals.py
django_enterprise_maintenance_suite/urls.py
django_enterprise_maintenance_suite/views.py
django_enterprise_maintenance_suite/management/commands/maintenance.py
django_enterprise_maintenance_suite/services/audit.py
django_enterprise_maintenance_suite/services/exceptions.py
django_enterprise_maintenance_suite/services/maintenance.py
django_enterprise_maintenance_suite/templates/503.html
django_enterprise_maintenance_suite-1.0.1.dist-info/licenses/LICENSE
django_enterprise_maintenance_suite-1.0.1.dist-info/METADATA
django_enterprise_maintenance_suite-1.0.1.dist-info/WHEEL
django_enterprise_maintenance_suite-1.0.1.dist-info/top_level.txt
django_enterprise_maintenance_suite-1.0.1.dist-info/RECORD
