Metadata-Version: 2.4
Name: django_enterprise_maintenance_suite
Version: 1.0.1
Summary: Enterprise Grade Maintenance Mode Management for Django Applications
Author-email: TS Tamarai Selvan <tamaraiselvan.official@gmail.com>
License: MIT License
Project-URL: Homepage, https://github.com/tamaraiselvan/Django-Enterprise-Maintenance-Suite
Project-URL: Source, https://github.com/tamaraiselvan/Django-Enterprise-Maintenance-Suite
Project-URL: Issues, https://github.com/tamaraiselvan/Django-Enterprise-Maintenance-Suite/issues
Keywords: django,maintenance,read-only,enterprise,applciations,middleware
Classifier: Framework :: Django
Classifier: Framework :: Django :: 4.2
Classifier: Programming Language :: Python :: 3
Classifier: Programming Language :: Python :: 3.9
Classifier: Programming Language :: Python :: 3.10
Classifier: Programming Language :: Python :: 3.11
Classifier: License :: OSI Approved :: MIT License
Classifier: Operating System :: OS Independent
Requires-Python: >=3.9
License-File: LICENSE
Requires-Dist: Django>=4.2
Dynamic: license-file
